LICENCE
setup.py
mocktest/__init__.py
mocktest/callrecord.py
mocktest/core.py
mocktest/mockerror.py
mocktest/mocking.py
mocktest/mocktest.py
mocktest/transaction.py
mocktest.egg-info/PKG-INFO
mocktest.egg-info/SOURCES.txt
mocktest.egg-info/dependency_links.txt
mocktest.egg-info/requires.txt
mocktest.egg-info/top_level.txt
mocktest/lib/__init__.py
mocktest/lib/realsetter.py
mocktest/lib/singletonclass.py
mocktest/matchers/__init__.py
mocktest/matchers/base.py
mocktest/matchers/collections.py
mocktest/matchers/string.py
mocktest/matchers/type_matcher.py