Metadata-Version: 1.1
Name: mocktest
Version: 0.7.3
Summary: mocking library for python, inspired by rspec
Home-page: http://gfxmonk.net/dist/doc/mocktest/doc/
Author: UNKNOWN
Author-email: UNKNOWN
License: UNKNOWN
Keywords: test mock expect expectation stub rspec unittest
Platform: UNKNOWN
Classifier: Programming Language :: Python
Classifier: Intended Audience :: Developers
Classifier: Topic :: Software Development :: Libraries :: Python Modules
Classifier: Topic :: Software Development :: Testing
Classifier: Programming Language :: Python :: 2
Classifier: Programming Language :: Python :: 3
